dicom_decompress/__init__.py
dicom_decompress/main.py
dicom_decompress-1.1.0.dist-info/LICENSE
dicom_decompress-1.1.0.dist-info/METADATA
dicom_decompress-1.1.0.dist-info/WHEEL
dicom_decompress-1.1.0.dist-info/entry_points.txt
dicom_decompress-1.1.0.dist-info/top_level.txt
dicom_decompress-1.1.0.dist-info/RECORD
