Metadata-Version: 2.1
Name: dicom-decompress
Version: 1.1.0
Summary: Minimal command-line tool for decompressing DICOM files with compressed pixel data.
Home-page: https://github.com/exini/dicom-decompress
Author: Karl Sjöstrand
Author-email: karl.sjostrand@exini.com
License: UNKNOWN
Platform: UNKNOWN
Classifier: License :: OSI Approved :: Apache Software License
Classifier: Programming Language :: Python :: 3
Classifier: Programming Language :: Python :: 3.8
Requires-Dist: numpy (==1.24.0)
Requires-Dist: pydicom (==2.4.4)
